wordhop
