Metadata-Version: 1.1
Name: wordhop
Version: 0.0.5
Summary: A toolkit for creating a hybrid Chatbot + Human UX
Home-page: https://github.com/wordhop-io/wordhop-python
Author: Michael Nathanson
Author-email: mike@wordhop.io
License: UNKNOWN
Download-URL: https://github.com/wordhop-io/wordhop-python/tarball/0.0.4
Keywords: chatbot,bot,opitmization,bot,analytics
Platform: UNKNOWN
